swisshydrodata/__init__.py
swisshydrodata-0.3.1.dist-info/LICENCE.md
swisshydrodata-0.3.1.dist-info/METADATA
swisshydrodata-0.3.1.dist-info/WHEEL
swisshydrodata-0.3.1.dist-info/top_level.txt
swisshydrodata-0.3.1.dist-info/RECORD
