Metadata-Version: 2.2
Name: swisshydrodata
Version: 0.3.1
Summary: A library to fetch data from the Swiss federal Office for Environment FEON
Author-email: bouni <bouni-github@owee.de>
Project-URL: Repository, https://github.com/Bouni/swisshydrodata
Project-URL: Documentation, https://github.com/Bouni/swisshydrodata
Project-URL: Releases, https://github.com/Bouni/swisshydrodata/releases
Platform: any
Requires-Python: >=3.12
License-File: LICENCE.md
